moderne_visualizations_misc/__init__.py
moderne_visualizations_misc/call_graph_data_grid.ipynb
moderne_visualizations_misc/call_graph_uml.ipynb
moderne_visualizations_misc/cobol_find_copybook.ipynb
moderne_visualizations_misc/cobol_relationships.ipynb
moderne_visualizations_misc/cobol_relationships_data_grid.ipynb
moderne_visualizations_misc/comment_language_distribution.ipynb
moderne_visualizations_misc/composite_recipe_results_sankey.ipynb
moderne_visualizations_misc/cyclomatic_complexity_heatmap.ipynb
moderne_visualizations_misc/cyclomatic_complexity_risk_matrix.ipynb
moderne_visualizations_misc/dependency_tree_view.ipynb
moderne_visualizations_misc/dependency_tree_view_nodejs.ipynb
moderne_visualizations_misc/dependency_tree_view_nodejs_build_tools.ipynb
moderne_visualizations_misc/dependency_tree_view_nodejs_db.ipynb
moderne_visualizations_misc/dependency_tree_view_nodejs_forms.ipynb
moderne_visualizations_misc/dependency_tree_view_nodejs_lint.ipynb
moderne_visualizations_misc/dependency_tree_view_nodejs_rtc.ipynb
moderne_visualizations_misc/dependency_tree_view_nodejs_security.ipynb
moderne_visualizations_misc/dependency_tree_view_nodejs_ss.ipynb
moderne_visualizations_misc/dependency_tree_view_nodejs_state.ipynb
moderne_visualizations_misc/dependency_tree_view_nodejs_testing.ipynb
moderne_visualizations_misc/dependency_tree_view_nodejs_ui.ipynb
moderne_visualizations_misc/dependency_tree_view_nodejs_utility.ipynb
moderne_visualizations_misc/dependency_usage_violin.ipynb
moderne_visualizations_misc/dependency_usage_violin_gradle.ipynb
moderne_visualizations_misc/dependency_usage_violin_jackson.ipynb
moderne_visualizations_misc/dependency_usage_violin_maven.ipynb
moderne_visualizations_misc/dependency_usage_violin_nodejs.ipynb
moderne_visualizations_misc/dependency_usage_violin_nodejs_build_tools.ipynb
moderne_visualizations_misc/dependency_usage_violin_nodejs_db.ipynb
moderne_visualizations_misc/dependency_usage_violin_nodejs_forms.ipynb
moderne_visualizations_misc-0.76.0.dist-info/licenses/LICENSE
moderne_visualizations_misc-0.76.0.dist-info/METADATA
moderne_visualizations_misc-0.76.0.dist-info/WHEEL
moderne_visualizations_misc-0.76.0.dist-info/top_level.txt
moderne_visualizations_misc-0.76.0.dist-info/RECORD
