Metadata-Version: 2.4
Name: moderne_visualizations_misc
Version: 0.76.0
Summary: Miscellaneous visualizations for the Moderne platform
Author-email: Jonathan Schneider <jonathan@moderne.io>, Kyle Scully <kyle@moderne.io>
License: Apache-2.0
Project-URL: Homepage, https://github.com/moderneinc/visualizations-misc
Requires-Python: >=3.9
License-File: LICENSE
Requires-Dist: code-data-science==2.1.2
Requires-Dist: graphviz==0.20.1
Requires-Dist: ipython==8.13.0
Requires-Dist: matplotlib==3.7.1
Requires-Dist: nbformat==5.9.0
Requires-Dist: pandas==2.0.3
Requires-Dist: plotly==5.14.1
Requires-Dist: typing-extensions
Requires-Dist: umap-learn==0.5.5
Requires-Dist: networkx==3.1
Requires-Dist: numpy==1.24.4
Dynamic: license-file
